[
  {
    "name": "Keucereus Base North",
    "kind": "Script",
    "min_height": -1000,
    "max_height": 6200,
    "points": [
      {
        "x": -193315,
        "y": 240184
      },
      {
        "x": -188053,
        "y": 235278
      },
      {
        "x": -179811,
        "y": 238353
      },
      {
        "x": -178407,
        "y": 242454
      },
      {
        "x": -178685,
        "y": 244665
      }
    ]
  },
  {
    "name": "Keucereus Base South",
    "kind": "Script",
    "min_height": -1000,
    "max_height": 6200,
    "points": [
      {
        "x": -178685,
        "y": 244664
      },
      {
        "x": -180120,
        "y": 246779
      },
      {
        "x": -185598,
        "y": 249572
      },
      {
        "x": -193009,
        "y": 245647
      },
      {
        "x": -193315,
        "y": 240185
      }
    ]
  },
  {
    "name": "14_25_keucereus alliance base_1",
    "kind": "Landing",
    "min_height": 1341,
    "max_height": 1691,
    "points": [
      {
        "x": -186340,
        "y": 245594
      },
      {
        "x": -186132,
        "y": 245657
      },
      {
        "x": -186557,
        "y": 246967
      },
      {
        "x": -186731,
        "y": 186731
      }
    ]
  },
  {
    "name": "14_25_keucereus alliance base_2",
    "kind": "Landing",
    "min_height": 1247,
    "max_height": 1597,
    "points": [
      {
        "x": -187105,
        "y": 245922
      },
      {
        "x": -185682,
        "y": 246358
      },
      {
        "x": -185731,
        "y": 246500
      },
      {
        "x": -187153,
        "y": 246066
      }
    ]
  },
  {
    "name": "14_25_keucereus alliance base_3",
    "kind": "Landing",
    "min_height": 1281,
    "max_height": 1631,
    "points": [
      {
        "x": -184162,
        "y": 238475
      },
      {
        "x": -183993,
        "y": 238529
      },
      {
        "x": -184372,
        "y": 239849
      },
      {
        "x": -184592,
        "y": 239784
      }
    ]
  },
  {
    "name": "14_25_keucereus alliance base_4",
    "kind": "Landing",
    "min_height": 1231,
    "max_height": 1581,
    "points": [
      {
        "x": -184991,
        "y": 238956
      },
      {
        "x": -183568,
        "y": 239392
      },
      {
        "x": -183617,
        "y": 239535
      },
      {
        "x": -185039,
        "y": 239100
      }
    ]
  },
  {
    "name": "14_25_keucereus alliance base_5",
    "kind": "Landing",
    "min_height": 2777,
    "max_height": 3127,
    "points": [
      {
        "x": -186159,
        "y": 240220
      },
      {
        "x": -185413,
        "y": 240447
      },
      {
        "x": -185454,
        "y": 240583
      },
      {
        "x": -186207,
        "y": 240357
      }
    ]
  },
  {
    "name": "14_25_keucereus alliance base_6",
    "kind": "Landing",
    "min_height": 2758,
    "max_height": 3108,
    "points": [
      {
        "x": -185773,
        "y": 240404
      },
      {
        "x": -185623,
        "y": 240452
      },
      {
        "x": -185683,
        "y": 240643
      },
      {
        "x": -185840,
        "y": 240596
      }
    ]
  },
  {
    "name": "14_25_keucereus alliance base_7",
    "kind": "Landing",
    "min_height": 1341,
    "max_height": 1691,
    "points": [
      {
        "x": -186340,
        "y": 245594
      },
      {
        "x": -186132,
        "y": 245657
      },
      {
        "x": -186557,
        "y": 246967
      },
      {
        "x": -186731,
        "y": 246909
      }
    ]
  },
  {
    "name": "14_25_keucereus alliance base_8",
    "kind": "Landing",
    "min_height": 1247,
    "max_height": 1597,
    "points": [
      {
        "x": -187105,
        "y": 245922
      },
      {
        "x": -185682,
        "y": 246358
      },
      {
        "x": -185731,
        "y": 246500
      },
      {
        "x": -187153,
        "y": 246066
      }
    ]
  },
  {
    "name": "14_25_keucereus alliance base_9",
    "kind": "Landing",
    "min_height": 1281,
    "max_height": 1631,
    "points": [
      {
        "x": -184162,
        "y": 238475
      },
      {
        "x": -183993,
        "y": 238529
      },
      {
        "x": -184372,
        "y": 239849
      },
      {
        "x": -184592,
        "y": 239784
      }
    ]
  },
  {
    "name": "14_25_keucereus alliance base_10",
    "kind": "Landing",
    "min_height": 1231,
    "max_height": 1581,
    "points": [
      {
        "x": -184991,
        "y": 238956
      },
      {
        "x": -183568,
        "y": 239392
      },
      {
        "x": -183617,
        "y": 239535
      },
      {
        "x": -185039,
        "y": 239100
      }
    ]
  },
  {
    "name": "14_25_keucereus alliance base_11",
    "kind": "Landing",
    "min_height": 2777,
    "max_height": 3127,
    "points": [
      {
        "x": -186159,
        "y": 240220
      },
      {
        "x": -185413,
        "y": 240447
      },
      {
        "x": -185454,
        "y": 240583
      },
      {
        "x": -186207,
        "y": 240357
      }
    ]
  },
  {
    "name": "14_25_keucereus alliance base_12",
    "kind": "Landing",
    "min_height": 2758,
    "max_height": 3108,
    "points": [
      {
        "x": -185773,
        "y": 240404
      },
      {
        "x": -185623,
        "y": 240452
      },
      {
        "x": -185683,
        "y": 240643
      },
      {
        "x": -185840,
        "y": 240596
      }
    ]
  },
  {
    "name": "14_25_keucereus alliance base_13",
    "kind": "Landing",
    "min_height": 2512,
    "max_height": 2862,
    "points": [
      {
        "x": -186399,
        "y": 241771
      },
      {
        "x": -185651,
        "y": 242002
      },
      {
        "x": -186028,
        "y": 243186
      },
      {
        "x": -186770,
        "y": 242973
      }
    ]
  },
  {
    "name": "14_25_keucereus alliance base_14",
    "kind": "Landing",
    "min_height": 2584,
    "max_height": 2934,
    "points": [
      {
        "x": -186176,
        "y": 241050
      },
      {
        "x": -185383,
        "y": 241287
      },
      {
        "x": -185503,
        "y": 241690
      },
      {
        "x": -186313,
        "y": 241440
      }
    ]
  },
  {
    "name": "14_25_keucereus alliance base_15",
    "kind": "Landing",
    "min_height": 2572,
    "max_height": 2922,
    "points": [
      {
        "x": -186866,
        "y": 243248
      },
      {
        "x": -186068,
        "y": 243492
      },
      {
        "x": -186205,
        "y": 243928
      },
      {
        "x": -187003,
        "y": 243678
      }
    ]
  },
  {
    "name": "14_25_keucereus alliance base_16",
    "kind": "Landing",
    "min_height": 2504,
    "max_height": 2854,
    "points": [
      {
        "x": -186993,
        "y": 242155
      },
      {
        "x": -186545,
        "y": 242296
      },
      {
        "x": -186587,
        "y": 242427
      },
      {
        "x": -187041,
        "y": 242295
      }
    ]
  },
  {
    "name": "14_25_keucereus alliance base_17",
    "kind": "Landing",
    "min_height": 2116,
    "max_height": 2466,
    "points": [
      {
        "x": -187557,
        "y": 244115
      },
      {
        "x": -187210,
        "y": 244222
      },
      {
        "x": -187260,
        "y": 244377
      },
      {
        "x": -187607,
        "y": 244271
      }
    ]
  },
  {
    "name": "14_25_keucereus alliance base_18",
    "kind": "Landing",
    "min_height": 2120,
    "max_height": 2470,
    "points": [
      {
        "x": -186368,
        "y": 240196
      },
      {
        "x": -186021,
        "y": 240301
      },
      {
        "x": -186068,
        "y": 240461
      },
      {
        "x": -186418,
        "y": 240344
      }
    ]
  },
  {
    "name": "14_25_keucereus alliance base_19",
    "kind": "Landing",
    "min_height": 1648,
    "max_height": 1818,
    "points": [
      {
        "x": -186750,
        "y": 242241
      },
      {
        "x": -186196,
        "y": 242418
      },
      {
        "x": -186232,
        "y": 242529
      },
      {
        "x": -186783,
        "y": 242358
      }
    ]
  },
  {
    "name": "14_25_keucereus alliance base_20",
    "kind": "Landing",
    "min_height": 1636,
    "max_height": 1986,
    "points": [
      {
        "x": -186049,
        "y": 241847
      },
      {
        "x": -185073,
        "y": 242132
      },
      {
        "x": -185437,
        "y": 243377
      },
      {
        "x": -186420,
        "y": 243106
      }
    ]
  },
  {
    "name": "14_25_keucereus alliance base_21",
    "kind": "Landing",
    "min_height": 1540,
    "max_height": 1890,
    "points": [
      {
        "x": -185124,
        "y": 242249
      },
      {
        "x": -183820,
        "y": 242643
      },
      {
        "x": -184113,
        "y": 243651
      },
      {
        "x": -185424,
        "y": 243257
      }
    ]
  },
  {
    "name": "14_25_keucereus alliance base_22",
    "kind": "Landing",
    "min_height": 1496,
    "max_height": 1846,
    "points": [
      {
        "x": -185257,
        "y": 243953
      },
      {
        "x": -184566,
        "y": 244156
      },
      {
        "x": -184958,
        "y": 245462
      },
      {
        "x": -185664,
        "y": 245254
      }
    ]
  },
  {
    "name": "14_25_keucereus alliance base_23",
    "kind": "Landing",
    "min_height": 1532,
    "max_height": 1882,
    "points": [
      {
        "x": -186768,
        "y": 243511
      },
      {
        "x": -185236,
        "y": 243954
      },
      {
        "x": -185619,
        "y": 245241
      },
      {
        "x": -187144,
        "y": 244768
      }
    ]
  },
  {
    "name": "14_25_keucereus alliance base_24",
    "kind": "Landing",
    "min_height": 1504,
    "max_height": 1854,
    "points": [
      {
        "x": -184240,
        "y": 240456
      },
      {
        "x": -183536,
        "y": 240664
      },
      {
        "x": -183931,
        "y": 241966
      },
      {
        "x": -184630,
        "y": 241758
      }
    ]
  },
  {
    "name": "14_25_keucereus alliance base_25",
    "kind": "Landing",
    "min_height": 1540,
    "max_height": 1890,
    "points": [
      {
        "x": -185715,
        "y": 240080
      },
      {
        "x": -184242,
        "y": 240529
      },
      {
        "x": -184610,
        "y": 241743
      },
      {
        "x": -186079,
        "y": 241297
      }
    ]
  },
  {
    "name": "14_25_keucereus alliance base_26",
    "kind": "Landing",
    "min_height": 1412,
    "max_height": 1762,
    "points": [
      {
        "x": -183713,
        "y": 241188
      },
      {
        "x": -182861,
        "y": 241456
      },
      {
        "x": -182933,
        "y": 241685
      },
      {
        "x": -183785,
        "y": 241440
      }
    ]
  },
  {
    "name": "14_25_keucereus alliance base_27",
    "kind": "Landing",
    "min_height": 1420,
    "max_height": 1770,
    "points": [
      {
        "x": -183970,
        "y": 243070
      },
      {
        "x": -183192,
        "y": 243307
      },
      {
        "x": -183234,
        "y": 243436
      },
      {
        "x": -184012,
        "y": 243212
      }
    ]
  },
  {
    "name": "14_25_keucereus alliance base_28",
    "kind": "Landing",
    "min_height": 1400,
    "max_height": 1750,
    "points": [
      {
        "x": -183705,
        "y": 243014
      },
      {
        "x": -182918,
        "y": 243257
      },
      {
        "x": -183037,
        "y": 243636
      },
      {
        "x": -183829,
        "y": 243425
      }
    ]
  },
  {
    "name": "14_25_keucereus alliance base_29",
    "kind": "Landing",
    "min_height": 1416,
    "max_height": 1766,
    "points": [
      {
        "x": -184756,
        "y": 244675
      },
      {
        "x": -183905,
        "y": 244939
      },
      {
        "x": -183978,
        "y": 245176
      },
      {
        "x": -184834,
        "y": 244930
      }
    ]
  },
  {
    "name": "14_25_keucereus alliance base_30",
    "kind": "Landing",
    "min_height": 1500,
    "max_height": 1850,
    "points": [
      {
        "x": -184243,
        "y": 241780
      },
      {
        "x": -183975,
        "y": 241853
      },
      {
        "x": -184190,
        "y": 242553
      },
      {
        "x": -184454,
        "y": 242489
      }
    ]
  },
  {
    "name": "14_25_keucereus alliance base_31",
    "kind": "Landing",
    "min_height": 1504,
    "max_height": 1854,
    "points": [
      {
        "x": -184742,
        "y": 243451
      },
      {
        "x": -184484,
        "y": 243522
      },
      {
        "x": -184676,
        "y": 244154
      },
      {
        "x": -184929,
        "y": 244069
      }
    ]
  },
  {
    "name": "14_25_keucereus alliance base_32",
    "kind": "Landing",
    "min_height": 1544,
    "max_height": 1844,
    "points": [
      {
        "x": -186154,
        "y": 243161
      },
      {
        "x": -185876,
        "y": 243242
      },
      {
        "x": -186038,
        "y": 243744
      },
      {
        "x": -186298,
        "y": 243669
      }
    ]
  },
  {
    "name": "14_25_keucereus alliance base_33",
    "kind": "Landing",
    "min_height": 1548,
    "max_height": 1848,
    "points": [
      {
        "x": -185619,
        "y": 241435
      },
      {
        "x": -185359,
        "y": 241501
      },
      {
        "x": -185499,
        "y": 241995
      },
      {
        "x": -185772,
        "y": 241918
      }
    ]
  },
  {
    "name": "14_25_keucereus alliance base_34",
    "kind": "Landing",
    "min_height": 2516,
    "max_height": 2716,
    "points": [
      {
        "x": -186102,
        "y": 241478
      },
      {
        "x": -185706,
        "y": 241597
      },
      {
        "x": -185810,
        "y": 241922
      },
      {
        "x": -186200,
        "y": 241806
      }
    ]
  },
  {
    "name": "14_25_keucereus alliance base_35",
    "kind": "Landing",
    "min_height": 2520,
    "max_height": 2720,
    "points": [
      {
        "x": -186562,
        "y": 243015
      },
      {
        "x": -186176,
        "y": 243125
      },
      {
        "x": -186273,
        "y": 243451
      },
      {
        "x": -186663,
        "y": 243329
      }
    ]
  },
  {
    "name": "14_25_kserth01",
    "kind": "NoSummonFriend",
    "min_height": 534,
    "max_height": 4534,
    "points": [
      {
        "x": -185793,
        "y": 237221
      },
      {
        "x": -179675,
        "y": 239239
      },
      {
        "x": -182132,
        "y": 249166
      },
      {
        "x": -189240,
        "y": 247252
      }
    ]
  },
  {
    "name": "base_kserth_peace1",
    "kind": "Peace",
    "min_height": 1103,
    "max_height": 3103,
    "points": [
      {
        "x": -183709,
        "y": 237556
      },
      {
        "x": -181798,
        "y": 241875
      },
      {
        "x": -182894,
        "y": 245386
      },
      {
        "x": -186902,
        "y": 247724
      },
      {
        "x": -188573,
        "y": 247186
      },
      {
        "x": -185574,
        "y": 237097
      }
    ]
  },
  {
    "name": "13_25_water1",
    "kind": "Water",
    "min_height": -4779,
    "max_height": -3779,
    "points": [
      {
        "x": -229376,
        "y": 229375
      },
      {
        "x": -196608,
        "y": 262143
      }
    ],
    "shape": "Cuboid"
  },
  {
    "name": "14_25_water2",
    "kind": "Water",
    "min_height": -2192,
    "max_height": -144,
    "points": [
      {
        "x": -187152,
        "y": 240401
      },
      {
        "x": -183376,
        "y": 245393
      }
    ],
    "shape": "Cuboid"
  },
  {
    "name": "14_25_water3",
    "kind": "Water",
    "min_height": -2192,
    "max_height": -144,
    "points": [
      {
        "x": -183376,
        "y": 241768
      },
      {
        "x": -182032,
        "y": 244872
      }
    ],
    "shape": "Cuboid"
  },
  {
    "name": "14_25_water4",
    "kind": "Water",
    "min_height": -2192,
    "max_height": -144,
    "points": [
      {
        "x": -183376,
        "y": 240968
      },
      {
        "x": -182799,
        "y": 241768
      }
    ],
    "shape": "Cuboid"
  }
]