{
    "1": {
        "MaxHp": 101.0,
        "MaxMp": 40.0,
        "MaxCp": 50.5,
        "HpRegen": 2.0,
        "MpRegen": 0.9,
        "CpRegen": 2.0
    },
    "2": {
        "MaxHp": 116.47,
        "MaxMp": 47.28,
        "MaxCp": 58.235,
        "HpRegen": 2.05,
        "MpRegen": 0.9,
        "CpRegen": 2.0
    },
    "3": {
        "MaxHp": 132.11,
        "MaxMp": 54.64,
        "MaxCp": 66.055,
        "HpRegen": 2.1,
        "MpRegen": 0.9,
        "CpRegen": 2.0
    },
    "4": {
        "MaxHp": 147.92,
        "MaxMp": 62.08,
        "MaxCp": 73.96,
        "HpRegen": 2.15,
        "MpRegen": 0.9,
        "CpRegen": 2.0
    },
    "5": {
        "MaxHp": 163.9,
        "MaxMp": 69.6,
        "MaxCp": 81.95,
        "HpRegen": 2.2,
        "MpRegen": 0.9,
        "CpRegen": 2.0
    },
    "6": {
        "MaxHp": 180.05,
        "MaxMp": 77.2,
        "MaxCp": 90.025,
        "HpRegen": 2.25,
        "MpRegen": 0.9,
        "CpRegen": 2.0
    },
    "7": {
        "MaxHp": 196.37,
        "MaxMp": 84.88,
        "MaxCp": 98.185,
        "HpRegen": 2.3,
        "MpRegen": 0.9,
        "CpRegen": 2.0
    },
    "8": {
        "MaxHp": 212.86,
        "MaxMp": 92.64,
        "MaxCp": 106.43,
        "HpRegen": 2.35,
        "MpRegen": 0.9,
        "CpRegen": 2.0
    },
    "9": {
        "MaxHp": 229.52,
        "MaxMp": 100.48,
        "MaxCp": 114.76,
        "HpRegen": 2.4,
        "MpRegen": 0.9,
        "CpRegen": 2.0
    },
    "10": {
        "MaxHp": 246.35,
        "MaxMp": 108.4,
        "MaxCp": 123.175,
        "HpRegen": 2.45,
        "MpRegen": 0.9,
        "CpRegen": 2.0
    },
    "11": {
        "MaxHp": 263.35,
        "MaxMp": 116.4,
        "MaxCp": 131.675,
        "HpRegen": 2.5,
        "MpRegen": 1.2,
        "CpRegen": 2.5
    },
    "12": {
        "MaxHp": 280.52,
        "MaxMp": 124.48,
        "MaxCp": 140.26,
        "HpRegen": 2.6,
        "MpRegen": 1.2,
        "CpRegen": 2.5
    },
    "13": {
        "MaxHp": 297.86,
        "MaxMp": 132.64,
        "MaxCp": 148.93,
        "HpRegen": 2.7,
        "MpRegen": 1.2,
        "CpRegen": 2.5
    },
    "14": {
        "MaxHp": 315.37,
        "MaxMp": 140.88,
        "MaxCp": 157.685,
        "HpRegen": 2.8,
        "MpRegen": 1.2,
        "CpRegen": 2.5
    },
    "15": {
        "MaxHp": 333.05,
        "MaxMp": 149.2,
        "MaxCp": 166.525,
        "HpRegen": 2.9,
        "MpRegen": 1.2,
        "CpRegen": 2.5
    },
    "16": {
        "MaxHp": 350.9,
        "MaxMp": 157.6,
        "MaxCp": 175.45,
        "HpRegen": 3.0,
        "MpRegen": 1.2,
        "CpRegen": 2.5
    },
    "17": {
        "MaxHp": 368.92,
        "MaxMp": 166.08,
        "MaxCp": 184.46,
        "HpRegen": 3.1,
        "MpRegen": 1.2,
        "CpRegen": 2.5
    },
    "18": {
        "MaxHp": 387.11,
        "MaxMp": 174.64,
        "MaxCp": 193.555,
        "HpRegen": 3.2,
        "MpRegen": 1.2,
        "CpRegen": 2.5
    },
    "19": {
        "MaxHp": 405.47,
        "MaxMp": 183.28,
        "MaxCp": 202.735,
        "HpRegen": 3.3,
        "MpRegen": 1.2,
        "CpRegen": 2.5
    },
    "20": {
        "MaxHp": 424.0,
        "MaxMp": 192.0,
        "MaxCp": 212.0,
        "HpRegen": 3.4,
        "MpRegen": 1.2,
        "CpRegen": 2.5
    },
    "21": {
        "MaxHp": 458.1,
        "MaxMp": 205.2,
        "MaxCp": 229.05,
        "HpRegen": 3.5,
        "MpRegen": 1.5,
        "CpRegen": 3.5
    },
    "22": {
        "MaxHp": 492.51,
        "MaxMp": 218.52,
        "MaxCp": 246.255,
        "HpRegen": 3.6,
        "MpRegen": 1.5,
        "CpRegen": 3.5
    },
    "23": {
        "MaxHp": 527.23,
        "MaxMp": 231.96,
        "MaxCp": 263.615,
        "HpRegen": 3.7,
        "MpRegen": 1.5,
        "CpRegen": 3.5
    },
    "24": {
        "MaxHp": 562.26,
        "MaxMp": 245.52,
        "MaxCp": 281.13,
        "HpRegen": 3.8,
        "MpRegen": 1.5,
        "CpRegen": 3.5
    },
    "25": {
        "MaxHp": 597.6,
        "MaxMp": 259.2,
        "MaxCp": 298.8,
        "HpRegen": 3.9,
        "MpRegen": 1.5,
        "CpRegen": 3.5
    },
    "26": {
        "MaxHp": 633.25,
        "MaxMp": 273.0,
        "MaxCp": 316.625,
        "HpRegen": 4.0,
        "MpRegen": 1.5,
        "CpRegen": 3.5
    },
    "27": {
        "MaxHp": 669.21,
        "MaxMp": 286.92,
        "MaxCp": 334.605,
        "HpRegen": 4.1,
        "MpRegen": 1.5,
        "CpRegen": 3.5
    },
    "28": {
        "MaxHp": 705.48,
        "MaxMp": 300.96,
        "MaxCp": 352.74,
        "HpRegen": 4.2,
        "MpRegen": 1.5,
        "CpRegen": 3.5
    },
    "29": {
        "MaxHp": 742.06,
        "MaxMp": 315.12,
        "MaxCp": 371.03,
        "HpRegen": 4.3,
        "MpRegen": 1.5,
        "CpRegen": 3.5
    },
    "30": {
        "MaxHp": 778.95,
        "MaxMp": 329.4,
        "MaxCp": 389.475,
        "HpRegen": 4.4,
        "MpRegen": 1.5,
        "CpRegen": 3.5
    },
    "31": {
        "MaxHp": 816.15,
        "MaxMp": 343.8,
        "MaxCp": 408.075,
        "HpRegen": 4.5,
        "MpRegen": 1.8,
        "CpRegen": 4.5
    },
    "32": {
        "MaxHp": 853.66,
        "MaxMp": 358.32,
        "MaxCp": 426.83,
        "HpRegen": 4.6,
        "MpRegen": 1.8,
        "CpRegen": 4.5
    },
    "33": {
        "MaxHp": 891.48,
        "MaxMp": 372.96,
        "MaxCp": 445.74,
        "HpRegen": 4.7,
        "MpRegen": 1.8,
        "CpRegen": 4.5
    },
    "34": {
        "MaxHp": 929.61,
        "MaxMp": 387.72,
        "MaxCp": 464.805,
        "HpRegen": 4.8,
        "MpRegen": 1.8,
        "CpRegen": 4.5
    },
    "35": {
        "MaxHp": 968.05,
        "MaxMp": 402.6,
        "MaxCp": 484.025,
        "HpRegen": 4.9,
        "MpRegen": 1.8,
        "CpRegen": 4.5
    },
    "36": {
        "MaxHp": 1006.8,
        "MaxMp": 417.6,
        "MaxCp": 503.4,
        "HpRegen": 5.0,
        "MpRegen": 1.8,
        "CpRegen": 4.5
    },
    "37": {
        "MaxHp": 1045.86,
        "MaxMp": 432.72,
        "MaxCp": 522.93,
        "HpRegen": 5.1,
        "MpRegen": 1.8,
        "CpRegen": 4.5
    },
    "38": {
        "MaxHp": 1085.23,
        "MaxMp": 447.96,
        "MaxCp": 542.615,
        "HpRegen": 5.2,
        "MpRegen": 1.8,
        "CpRegen": 4.5
    },
    "39": {
        "MaxHp": 1124.91,
        "MaxMp": 463.32,
        "MaxCp": 562.455,
        "HpRegen": 5.3,
        "MpRegen": 1.8,
        "CpRegen": 4.5
    },
    "40": {
        "MaxHp": 1164.9,
        "MaxMp": 478.8,
        "MaxCp": 582.45,
        "HpRegen": 5.4,
        "MpRegen": 1.8,
        "CpRegen": 4.5
    },
    "41": {
        "MaxHp": 1205.2,
        "MaxMp": 494.4,
        "MaxCp": 602.6,
        "HpRegen": 5.5,
        "MpRegen": 2.1,
        "CpRegen": 5.5
    },
    "42": {
        "MaxHp": 1245.81,
        "MaxMp": 510.12,
        "MaxCp": 622.905,
        "HpRegen": 5.6,
        "MpRegen": 2.1,
        "CpRegen": 5.5
    },
    "43": {
        "MaxHp": 1286.73,
        "MaxMp": 525.96,
        "MaxCp": 643.365,
        "HpRegen": 5.7,
        "MpRegen": 2.1,
        "CpRegen": 5.5
    },
    "44": {
        "MaxHp": 1327.96,
        "MaxMp": 541.92,
        "MaxCp": 663.98,
        "HpRegen": 5.8,
        "MpRegen": 2.1,
        "CpRegen": 5.5
    },
    "45": {
        "MaxHp": 1369.5,
        "MaxMp": 558.0,
        "MaxCp": 684.75,
        "HpRegen": 5.9,
        "MpRegen": 2.1,
        "CpRegen": 5.5
    },
    "46": {
        "MaxHp": 1411.35,
        "MaxMp": 574.2,
        "MaxCp": 705.675,
        "HpRegen": 6.0,
        "MpRegen": 2.1,
        "CpRegen": 5.5
    },
    "47": {
        "MaxHp": 1453.51,
        "MaxMp": 590.52,
        "MaxCp": 726.755,
        "HpRegen": 6.1,
        "MpRegen": 2.1,
        "CpRegen": 5.5
    },
    "48": {
        "MaxHp": 1495.98,
        "MaxMp": 606.96,
        "MaxCp": 747.99,
        "HpRegen": 6.2,
        "MpRegen": 2.1,
        "CpRegen": 5.5
    },
    "49": {
        "MaxHp": 1538.76,
        "MaxMp": 623.52,
        "MaxCp": 769.38,
        "HpRegen": 6.3,
        "MpRegen": 2.1,
        "CpRegen": 5.5
    },
    "50": {
        "MaxHp": 1581.85,
        "MaxMp": 640.2,
        "MaxCp": 790.925,
        "HpRegen": 6.4,
        "MpRegen": 2.1,
        "CpRegen": 5.5
    },
    "51": {
        "MaxHp": 1625.25,
        "MaxMp": 657.0,
        "MaxCp": 812.625,
        "HpRegen": 6.5,
        "MpRegen": 2.4,
        "CpRegen": 6.5
    },
    "52": {
        "MaxHp": 1668.96,
        "MaxMp": 673.92,
        "MaxCp": 834.48,
        "HpRegen": 6.6,
        "MpRegen": 2.4,
        "CpRegen": 6.5
    },
    "53": {
        "MaxHp": 1712.98,
        "MaxMp": 690.96,
        "MaxCp": 856.49,
        "HpRegen": 6.7,
        "MpRegen": 2.4,
        "CpRegen": 6.5
    },
    "54": {
        "MaxHp": 1757.31,
        "MaxMp": 708.12,
        "MaxCp": 878.655,
        "HpRegen": 6.8,
        "MpRegen": 2.4,
        "CpRegen": 6.5
    },
    "55": {
        "MaxHp": 1801.95,
        "MaxMp": 725.4,
        "MaxCp": 900.975,
        "HpRegen": 6.9,
        "MpRegen": 2.4,
        "CpRegen": 6.5
    },
    "56": {
        "MaxHp": 1846.9,
        "MaxMp": 742.8,
        "MaxCp": 923.45,
        "HpRegen": 7.0,
        "MpRegen": 2.4,
        "CpRegen": 6.5
    },
    "57": {
        "MaxHp": 1892.16,
        "MaxMp": 760.32,
        "MaxCp": 946.08,
        "HpRegen": 7.1,
        "MpRegen": 2.4,
        "CpRegen": 6.5
    },
    "58": {
        "MaxHp": 1937.73,
        "MaxMp": 777.96,
        "MaxCp": 968.865,
        "HpRegen": 7.2,
        "MpRegen": 2.4,
        "CpRegen": 6.5
    },
    "59": {
        "MaxHp": 1983.61,
        "MaxMp": 795.72,
        "MaxCp": 991.805,
        "HpRegen": 7.3,
        "MpRegen": 2.4,
        "CpRegen": 6.5
    },
    "60": {
        "MaxHp": 2029.8,
        "MaxMp": 813.6,
        "MaxCp": 1014.9,
        "HpRegen": 7.4,
        "MpRegen": 2.4,
        "CpRegen": 6.5
    },
    "61": {
        "MaxHp": 2076.3,
        "MaxMp": 831.6,
        "MaxCp": 1038.15,
        "HpRegen": 7.5,
        "MpRegen": 2.7,
        "CpRegen": 7.5
    },
    "62": {
        "MaxHp": 2123.11,
        "MaxMp": 849.72,
        "MaxCp": 1061.555,
        "HpRegen": 7.6,
        "MpRegen": 2.7,
        "CpRegen": 7.5
    },
    "63": {
        "MaxHp": 2170.23,
        "MaxMp": 867.96,
        "MaxCp": 1085.115,
        "HpRegen": 7.7,
        "MpRegen": 2.7,
        "CpRegen": 7.5
    },
    "64": {
        "MaxHp": 2217.66,
        "MaxMp": 886.32,
        "MaxCp": 1108.83,
        "HpRegen": 7.8,
        "MpRegen": 2.7,
        "CpRegen": 7.5
    },
    "65": {
        "MaxHp": 2265.4,
        "MaxMp": 904.8,
        "MaxCp": 1132.7,
        "HpRegen": 7.9,
        "MpRegen": 2.7,
        "CpRegen": 7.5
    },
    "66": {
        "MaxHp": 2313.45,
        "MaxMp": 923.4,
        "MaxCp": 1156.725,
        "HpRegen": 8.0,
        "MpRegen": 2.7,
        "CpRegen": 7.5
    },
    "67": {
        "MaxHp": 2361.81,
        "MaxMp": 942.12,
        "MaxCp": 1180.905,
        "HpRegen": 8.1,
        "MpRegen": 2.7,
        "CpRegen": 7.5
    },
    "68": {
        "MaxHp": 2410.48,
        "MaxMp": 960.96,
        "MaxCp": 1205.24,
        "HpRegen": 8.2,
        "MpRegen": 2.7,
        "CpRegen": 7.5
    },
    "69": {
        "MaxHp": 2459.46,
        "MaxMp": 979.92,
        "MaxCp": 1229.73,
        "HpRegen": 8.3,
        "MpRegen": 2.7,
        "CpRegen": 7.5
    },
    "70": {
        "MaxHp": 2508.75,
        "MaxMp": 999.0,
        "MaxCp": 1254.375,
        "HpRegen": 8.4,
        "MpRegen": 2.7,
        "CpRegen": 7.5
    },
    "71": {
        "MaxHp": 2558.35,
        "MaxMp": 1018.2,
        "MaxCp": 1279.175,
        "HpRegen": 8.5,
        "MpRegen": 3.0,
        "CpRegen": 8.5
    },
    "72": {
        "MaxHp": 2608.26,
        "MaxMp": 1037.52,
        "MaxCp": 1304.13,
        "HpRegen": 8.6,
        "MpRegen": 3.0,
        "CpRegen": 8.5
    },
    "73": {
        "MaxHp": 2658.48,
        "MaxMp": 1056.96,
        "MaxCp": 1329.24,
        "HpRegen": 8.7,
        "MpRegen": 3.0,
        "CpRegen": 8.5
    },
    "74": {
        "MaxHp": 2709.01,
        "MaxMp": 1076.52,
        "MaxCp": 1354.505,
        "HpRegen": 8.8,
        "MpRegen": 3.0,
        "CpRegen": 8.5
    },
    "75": {
        "MaxHp": 2759.85,
        "MaxMp": 1096.2,
        "MaxCp": 1379.925,
        "HpRegen": 8.9,
        "MpRegen": 3.0,
        "CpRegen": 8.5
    },
    "76": {
        "MaxHp": 2811.0,
        "MaxMp": 1116.0,
        "MaxCp": 1405.5,
        "HpRegen": 9.0,
        "MpRegen": 3.0,
        "CpRegen": 8.5
    },
    "77": {
        "MaxHp": 2862.46,
        "MaxMp": 1135.92,
        "MaxCp": 1431.23,
        "HpRegen": 9.1,
        "MpRegen": 3.0,
        "CpRegen": 8.5
    },
    "78": {
        "MaxHp": 2914.23,
        "MaxMp": 1155.96,
        "MaxCp": 1457.115,
        "HpRegen": 9.2,
        "MpRegen": 3.0,
        "CpRegen": 8.5
    },
    "79": {
        "MaxHp": 2966.31,
        "MaxMp": 1176.12,
        "MaxCp": 1483.155,
        "HpRegen": 9.3,
        "MpRegen": 3.0,
        "CpRegen": 8.5
    },
    "80": {
        "MaxHp": 3018.7,
        "MaxMp": 1196.4,
        "MaxCp": 1509.35,
        "HpRegen": 9.4,
        "MpRegen": 3.0,
        "CpRegen": 8.5
    },
    "81": {
        "MaxHp": 3071.4,
        "MaxMp": 1216.8,
        "MaxCp": 1535.7,
        "HpRegen": 9.5,
        "MpRegen": 3.0,
        "CpRegen": 8.5
    },
    "82": {
        "MaxHp": 3124.41,
        "MaxMp": 1237.32,
        "MaxCp": 1562.205,
        "HpRegen": 9.6,
        "MpRegen": 3.0,
        "CpRegen": 8.5
    },
    "83": {
        "MaxHp": 3177.73,
        "MaxMp": 1257.96,
        "MaxCp": 1588.865,
        "HpRegen": 9.7,
        "MpRegen": 3.0,
        "CpRegen": 8.5
    },
    "84": {
        "MaxHp": 3231.36,
        "MaxMp": 1278.72,
        "MaxCp": 1615.68,
        "HpRegen": 9.8,
        "MpRegen": 3.0,
        "CpRegen": 8.5
    },
    "85": {
        "MaxHp": 3285.3,
        "MaxMp": 1299.6,
        "MaxCp": 1642.65,
        "HpRegen": 9.9,
        "MpRegen": 3.0,
        "CpRegen": 8.5
    }
}